bdrc_irat/ActionContext.py
bdrc_irat/PsParser.py
bdrc_irat/__init__.py
bdrc_irat/action_fs_sizes.py
bdrc_irat/action_list.py
bdrc_irat/action_types.py
bdrc_irat/common.py
bdrc_irat/get_different_files.py
bdrc_irat/parallel_scan_test.py
bdrc_irat/scan_images.py
bdrc_irat-0.9.0.dist-info/METADATA
bdrc_irat-0.9.0.dist-info/WHEEL
bdrc_irat-0.9.0.dist-info/entry_points.txt
bdrc_irat-0.9.0.dist-info/top_level.txt
bdrc_irat-0.9.0.dist-info/RECORD
