Metadata-Version: 2.1
Name: bdrc-irat
Version: 0.9.0
Summary: Image Repository analysis
Home-page: https://github.com/buda-base/count-images/parallelscan
Author: jimk
Author-email: jimk@bdrc.io
License: UNKNOWN
Platform: UNKNOWN
Classifier: Programming Language :: Python :: 3
Classifier: License :: OSI Approved :: MIT License
Classifier: Operating System :: OS Independent
Classifier: Intended Audience :: System Administrators
Classifier: Development Status :: 3 - Alpha
Requires-Python: >=3.7
Requires-Dist: bdrc-util
Requires-Dist: pillow
Requires-Dist: boto3
Requires-Dist: s3pathlib
